Metadata-Version: 2.1
Name: django-softdeletion
Version: 0.1.1
Summary: django softdeletion
Home-page: https://github.com/AngelLiang/django-softdeletion
License: MIT
Platform: any
